langchain_olostep/__init__.py
langchain_olostep/tools.py
langchain_olostep-0.3.3.dist-info/licenses/LICENSE
langchain_olostep-0.3.3.dist-info/METADATA
langchain_olostep-0.3.3.dist-info/WHEEL
langchain_olostep-0.3.3.dist-info/top_level.txt
langchain_olostep-0.3.3.dist-info/RECORD
