Metadata-Version: 2.4
Name: langchain-olostep
Version: 0.3.3
Summary: The most reliable and cost-effective web search, scraping and crawling API for AI. Build intelligent agents that can search, scrape, analyze, and structure data from any website.
Home-page: https://github.com/olostep/langchain-olostep
Author: Olostep
Author-email: Olostep <info@olostep.com>
License: MIT
Project-URL: Homepage, https://github.com/olostep/langchain-olostep
Project-URL: Repository, https://github.com/olostep/langchain-olostep
Project-URL: Documentation, https://docs.olostep.com/integrations/langchain
Project-URL: Issues, https://github.com/olostep/langchain-olostep/issues
Keywords: langchain,langgraph,web-scraping,web-search,crawling,olostep,ai,llm,agents
Classifier: Development Status :: 4 - Beta
Classifier: Intended Audience :: Developers
Classifier: License :: OSI Approved :: MIT License
Classifier: Operating System :: OS Independent
Classifier: Programming Language :: Python :: 3
Classifier: Programming Language :: Python :: 3.9
Classifier: Programming Language :: Python :: 3.10
Classifier: Programming Language :: Python :: 3.11
Classifier: Programming Language :: Python :: 3.12
Classifier: Topic :: Software Development :: Libraries :: Python Modules
Classifier: Topic :: Internet :: WWW/HTTP :: Dynamic Content
Classifier: Topic :: Scientific/Engineering :: Artificial Intelligence
Requires-Python: >=3.9
License-File: LICENSE
Requires-Dist: langchain-core>=0.3.0
Requires-Dist: requests>=2.31.0
Requires-Dist: pydantic>=2.0.0
Provides-Extra: dev
Requires-Dist: pytest>=7.0.0; extra == "dev"
Requires-Dist: pytest-asyncio>=0.21.0; extra == "dev"
Requires-Dist: pytest-mock>=3.10.0; extra == "dev"
Requires-Dist: black>=23.0.0; extra == "dev"
Requires-Dist: isort>=5.12.0; extra == "dev"
Requires-Dist: flake8>=6.0.0; extra == "dev"
Requires-Dist: mypy>=1.0.0; extra == "dev"
Provides-Extra: test
Requires-Dist: pytest>=7.0.0; extra == "test"
Requires-Dist: pytest-asyncio>=0.21.0; extra == "test"
Requires-Dist: pytest-mock>=3.10.0; extra == "test"
Requires-Dist: httpx>=0.24.0; extra == "test"
Dynamic: author
Dynamic: home-page
Dynamic: license-file
Dynamic: requires-python
